{
  "coord": {
    "lon": 2.3488,
    "lat": 48.8534
  },
  "weather": [
    {
      "id": 804,
      "main": "Clouds",
      "description": "overcast clouds",
      "icon": "04n"
    }
  ],
  "base": "stations",
  "main": {
    "temp": 19.76,
    "feels_like": 19.7,
    "temp_min": 19.58,
    "temp_max": 20.04,
    "pressure": 1013,
    "humidity": 73,
    "sea_level": 1013,
    "grnd_level": 1004
  },
  "visibility": 10000,
  "wind": {
    "speed": 0.64,
    "deg": 300,
    "gust": 1.18
  },
  "clouds": {
    "all": 99
  },
  "dt": 1781577743,
  "sys": {
    "type": 2,
    "id": 66795,
    "country": "FR",
    "sunrise": 1781581592,
    "sunset": 1781639765
  },
  "timezone": 7200,
  "id": 2988507,
  "name": "Paris",
  "cod": 200,
  "_last_updated_utc": "2026-06-16T02:50:11.390Z"
}