{
  "coord": {
    "lon": 2.3488,
    "lat": 48.8534
  },
  "weather": [
    {
      "id": 802,
      "main": "Clouds",
      "description": "scattered clouds",
      "icon": "03d"
    }
  ],
  "base": "stations",
  "main": {
    "temp": 10.66,
    "feels_like": 9.56,
    "temp_min": 10.66,
    "temp_max": 10.66,
    "pressure": 1013,
    "humidity": 68,
    "sea_level": 1013,
    "grnd_level": 1004
  },
  "visibility": 10000,
  "wind": {
    "speed": 2.72,
    "deg": 53,
    "gust": 3.94
  },
  "clouds": {
    "all": 40
  },
  "dt": 1774174200,
  "sys": {
    "country": "FR",
    "sunrise": 1774158583,
    "sunset": 1774202717
  },
  "timezone": 3600,
  "id": 2988507,
  "name": "Paris",
  "cod": 200,
  "_last_updated_utc": "2026-03-22T10:18:30.227Z"
}