{
  "coord": {
    "lon": 2.3488,
    "lat": 48.8534
  },
  "weather": [
    {
      "id": 803,
      "main": "Clouds",
      "description": "broken clouds",
      "icon": "04n"
    }
  ],
  "base": "stations",
  "main": {
    "temp": 4.59,
    "feels_like": 1.36,
    "temp_min": 4.59,
    "temp_max": 4.59,
    "pressure": 1023,
    "humidity": 62,
    "sea_level": 1023,
    "grnd_level": 1013
  },
  "visibility": 10000,
  "wind": {
    "speed": 4,
    "deg": 353,
    "gust": 6.91
  },
  "clouds": {
    "all": 60
  },
  "dt": 1774556506,
  "sys": {
    "country": "FR",
    "sunrise": 1774503674,
    "sunset": 1774548675
  },
  "timezone": 3600,
  "id": 2988507,
  "name": "Paris",
  "cod": 200,
  "_last_updated_utc": "2026-03-26T20:27:50.000Z"
}